setup.cfg
setup.py
django_user_agent_detector/__init__.py
django_user_agent_detector.egg-info/PKG-INFO
django_user_agent_detector.egg-info/SOURCES.txt
django_user_agent_detector.egg-info/dependency_links.txt
django_user_agent_detector.egg-info/entry_points.txt
django_user_agent_detector.egg-info/top_level.txt
django_user_agent_detector.egg-info/zip-safe