Metadata-Version: 1.0
Name: django-user-agent-detector
Version: 0.1dev
Summary: Detect and handle desktop vs mobile user agents with django-annoying
Home-page: http://www.bitbucket.org/rwilcox/django-user_agent_detector
Author: Ryan Wilcox
Author-email: rwilcox@wilcoxd.com
License: BSD
Keywords: django django_annoying mobile iphone
Platform: UNKNOWN
